pcax/__init__.py
pcax/pca.py
pcax-0.1.0.dist-info/LICENSE
pcax-0.1.0.dist-info/METADATA
pcax-0.1.0.dist-info/WHEEL
pcax-0.1.0.dist-info/top_level.txt
pcax-0.1.0.dist-info/RECORD
