Metadata-Version: 2.1
Name: pcax
Version: 0.1.0
Summary: Minimal Principal Component Analysis (PCA) implementation using JAX.
Author-email: Albert Alonso <alonfnt@pm.me>
License: MIT License
Project-URL: Homepage, https://github.com/alonfnt/pcax
Project-URL: Documentation, https://github.com/alonfnt/pcax
Project-URL: Source, https://github.com/alonfnt/pcax
Project-URL: Bug Tracker, https://github.com/alonfnt/pcax/issues
Keywords: jax,pca,machine-learning
Classifier: Development Status :: 3 - Alpha
Classifier: Intended Audience :: Developers
Classifier: License :: OSI Approved :: MIT License
Classifier: Programming Language :: Python :: 3
Classifier: Programming Language :: Python :: 3.9
Classifier: Programming Language :: Python :: 3.10
Classifier: Programming Language :: Python :: 3.11
Requires-Python: >=3.9
License-File: LICENSE
